Metadata-Version: 2.1
Name: jensen-shannon-centroid
Version: 1.0
Summary: This package is used to calculate the Jensen-Shannon centroid of a set of categorical distributions.
Author: Dustin Wright
Author-email: dw@di.ku.dk
Requires-Python: >=3.6
License-File: LICENSE
